LICENSE
README.md
django_explorer/__init__.py
django_explorer/signals.py
django_explorer/templates/django_explorer/list_plain.html
django_explorer/templatetags/__init__.py
django_explorer/templatetags/django_explorer.py
django_explorer/templatetags/themes/__init__.py
django_explorer/templatetags/themes/plain.py
django_explorer/types.py
django_explorer/utils.py
django_explorer/views.py
django_explorer-0.3.0.dist-info/LICENSE
django_explorer-0.3.0.dist-info/WHEEL
django_explorer-0.3.0.dist-info/METADATA
django_explorer-0.3.0.dist-info/RECORD
